parspace.py
parspace-1.1.0.dist-info/LICENSE
parspace-1.1.0.dist-info/METADATA
parspace-1.1.0.dist-info/WHEEL
parspace-1.1.0.dist-info/top_level.txt
parspace-1.1.0.dist-info/RECORD
