Metadata-Version: 2.1
Name: parspace
Version: 1.1.0
Summary: Parameter space exploration utiliy.
Home-page: https://github.com/amorison/parspace
Author: Adrien Morison
Author-email: adrien.morison@gmail.com
License: Apache
Platform: UNKNOWN
Classifier: Development Status :: 5 - Production/Stable
Classifier: Intended Audience :: Science/Research
Classifier: License :: OSI Approved :: MIT License
Classifier: Programming Language :: Python :: 3 :: Only
Classifier: Programming Language :: Python :: 3.6
Classifier: Programming Language :: Python :: 3.7
Classifier: Programming Language :: Python :: 3.8
Classifier: Programming Language :: Python :: 3.9
Requires-Python: >=3.6
